Topsis/__init__.py
Topsis/__main__.py
Topsis_Samarjeet_102103145-1.1.dist-info/METADATA
Topsis_Samarjeet_102103145-1.1.dist-info/WHEEL
Topsis_Samarjeet_102103145-1.1.dist-info/entry_points.txt
Topsis_Samarjeet_102103145-1.1.dist-info/top_level.txt
Topsis_Samarjeet_102103145-1.1.dist-info/RECORD
