Metadata-Version: 2.1
Name: Topsis-Samarjeet-102103145
Version: 1.1
Summary: Topsis-Samarjeet-102103145
Home-page: https://github.com/gandhi25samar/Topsis-Samarjeet-102103145.git
Author: Samarjeet Singh Gandhi
Author-email: gandhi25samarjeet@gmail.com
License: MIT
Classifier: License :: OSI Approved :: MIT License
Classifier: Programming Language :: Python :: 3.6
Classifier: Programming Language :: Python :: 3.7
Classifier: Programming Language :: Python :: 3.8
